{
  "ticker": "EFC",
  "yf_symbol": "EFC",
  "_fetched_at": "2026-06-29T11:01:38.207691+00:00",
  "trailingPE": 8.376543,
  "forwardPE": 7.0327277,
  "priceToBook": 0.99545187,
  "debtToEquity": 906.074,
  "currentRatio": 8.095,
  "quickRatio": 8.08,
  "payoutRatio": 0.96300006,
  "freeCashflow": null,
  "operatingCashflow": -809020992,
  "revenueGrowth": 0.765,
  "earningsGrowth": 1.27,
  "earningsQuarterlyGrowth": 1.722,
  "dividendYield": 11.5,
  "returnOnEquity": 0.12178001,
  "returnOnAssets": 0.0118700005,
  "profitMargins": 0.53392,
  "trailingEps": 1.62,
  "forwardEps": 1.92955,
  "marketCap": 1701591424,
  "longName": "Ellington Financial Inc.",
  "sector": "Real Estate",
  "industry": "REIT - Mortgage",
  "_ok": true
}