{
  "ticker": "FNF",
  "yf_symbol": "FNF",
  "_fetched_at": "2026-06-29T11:00:29.372509+00:00",
  "trailingPE": 16.622776,
  "forwardPE": 7.89941,
  "priceToBook": 1.732117,
  "debtToEquity": 54.788,
  "currentRatio": 0.953,
  "quickRatio": 0.147,
  "payoutRatio": 0.726,
  "freeCashflow": 2113124992,
  "operatingCashflow": 5587999744,
  "revenueGrowth": 0.167,
  "earningsGrowth": 2.0,
  "earningsQuarterlyGrowth": 1.928,
  "dividendYield": 4.45,
  "returnOnEquity": 0.1047,
  "returnOnAssets": 0.0127799995,
  "profitMargins": 0.05092,
  "trailingEps": 2.81,
  "forwardEps": 5.9131,
  "marketCap": 12572348416,
  "longName": "Fidelity National Financial, Inc.",
  "sector": "Financial Services",
  "industry": "Insurance - Specialty",
  "_ok": true
}