{
  "ticker": "NFLX",
  "yf_symbol": "NFLX",
  "_fetched_at": "2026-06-29T10:59:29.713186+00:00",
  "trailingPE": 23.809677,
  "forwardPE": 19.209297,
  "priceToBook": 9.989173,
  "debtToEquity": 53.788,
  "currentRatio": 1.407,
  "quickRatio": 1.178,
  "payoutRatio": 0.0,
  "freeCashflow": 25993676800,
  "operatingCashflow": 12650278912,
  "revenueGrowth": 0.162,
  "earningsGrowth": 0.864,
  "earningsQuarterlyGrowth": 0.828,
  "dividendYield": null,
  "returnOnEquity": 0.48494998,
  "returnOnAssets": 0.15402001,
  "profitMargins": 0.28521,
  "trailingEps": 3.1,
  "forwardEps": 3.84241,
  "marketCap": 310799040512,
  "longName": "Netflix, Inc.",
  "sector": "Communication Services",
  "industry": "Entertainment",
  "_ok": true
}