{
  "ticker": "SWK",
  "yf_symbol": "SWK",
  "_fetched_at": "2026-06-15T19:59:42.715002+00:00",
  "trailingPE": 34.704918,
  "forwardPE": 13.583247,
  "priceToBook": 1.4663204,
  "debtToEquity": 77.606,
  "currentRatio": 1.138,
  "quickRatio": 0.31,
  "payoutRatio": 1.3566,
  "freeCashflow": 842187520,
  "operatingCashflow": 1002400000,
  "revenueGrowth": 0.027,
  "earningsGrowth": -0.348,
  "earningsQuarterlyGrowth": -0.341,
  "dividendYield": 3.97,
  "returnOnEquity": 0.04165,
  "returnOnAssets": 0.03329,
  "profitMargins": 0.024360001,
  "trailingEps": 2.44,
  "forwardEps": 6.23415,
  "marketCap": 13163977728,
  "longName": "Stanley Black & Decker, Inc.",
  "sector": "Industrials",
  "industry": "Tools & Accessories",
  "_ok": true
}